{"cameraMode":{"drawMode":0,"name":"Shaded","section":"Shading Mode"},"sceneLighting":true,"audioPlay":false,"sceneViewState":{"m_AlwaysRefresh":false,"showFog":true,"showSkybox":true,"showFlares":true,"showImageEffects":true,"showParticleSystems":true,"showVisualEffectGraphs":true,"m_FxEnabled":true},"in2DMode":false,"pivot":{"x":290.3926696777344,"y":276.9387512207031,"z":-246.13710021972657},"rotation":{"x":-0.2330866903066635,"y":0.15873950719833375,"z":-0.038603439927101138,"w":-0.9587064385414124},"size":203.9272918701172,"orthographic":false}